pydriver/__init__.py
pydriver/motor_driver.py
motordriverpkg-0.0.3.dist-info/METADATA
motordriverpkg-0.0.3.dist-info/WHEEL
motordriverpkg-0.0.3.dist-info/top_level.txt
motordriverpkg-0.0.3.dist-info/RECORD
