Metadata-Version: 2.1
Name: motordriverpkg
Version: 0.0.3
Summary: A package for controlling the motor driver
Home-page: UNKNOWN
Author: saravana kannan
Author-email: saravana.rae@gmail.com
License: UNKNOWN
Keywords: python,video,stream,video stream,camera stream,sockets
Platform: UNKNOWN
Classifier: Development Status :: 1 - Planning
Classifier: Intended Audience :: Developers
Classifier: Programming Language :: Python :: 3
Classifier: Operating System :: Unix
Classifier: Operating System :: MacOS :: MacOS X
Classifier: Operating System :: Microsoft :: Windows
Requires-Dist: pyserial
